huscy/recruitment/__init__.py
huscy/recruitment/apps.py
huscy/recruitment/models.py
huscy/recruitment/serializer.py
huscy/recruitment/services.py
huscy/recruitment/urls.py
huscy/recruitment/views.py
huscy/recruitment/migrations/.gitignore
huscy/recruitment/migrations/0001_initial.py
huscy/recruitment/migrations/__init__.py
huscy_recruitment-0.15.0a49.dist-info/METADATA
huscy_recruitment-0.15.0a49.dist-info/WHEEL
huscy_recruitment-0.15.0a49.dist-info/licenses/LICENSE
huscy_recruitment-0.15.0a49.dist-info/RECORD
