Metadata-Version: 2.4
Name: huscy.recruitment
Version: 0.15.0a49
Project-URL: Homepage, https://bitbucket.org/huscy/recruitment
Author-email: Alexander Tyapkov <tyapkov@gmail.com>, Anne-Cathrin Brenner <anne-cathrin-brenner@posteo.de>, Stefan Bunde <stefanbunde+git@posteo.de>
License-Expression: AGPL-3.0-or-later
License-File: LICENSE
Classifier: Development Status :: 3 - Alpha
Classifier: Framework :: Django
Classifier: Framework :: Django :: 4.2
Classifier: Framework :: Django :: 5.2
Classifier: Framework :: Django :: 6.0
Classifier: Operating System :: OS Independent
Classifier: Programming Language :: Python
Classifier: Programming Language :: Python :: 3
Classifier: Programming Language :: Python :: 3 :: Only
Classifier: Programming Language :: Python :: 3.10
Classifier: Programming Language :: Python :: 3.11
Classifier: Programming Language :: Python :: 3.12
Classifier: Programming Language :: Python :: 3.13
Classifier: Programming Language :: Python :: 3.14
Requires-Dist: huscy-attributes
Requires-Dist: huscy-participations
Requires-Dist: huscy-subject-contact-history
Requires-Dist: python-dateutil
Provides-Extra: development
Requires-Dist: psycopg2-binary; extra == 'development'
Provides-Extra: testing
Requires-Dist: tox; extra == 'testing'
Requires-Dist: watchdog; extra == 'testing'
